agentmeter/__init__.py
agentmeter/auth.py
agentmeter/cli.py
agentmeter/client.py
agentmeter/decorators.py
agentmeter/exceptions.py
agentmeter/langchain_integration.py
agentmeter/models.py
agentmeter/py.typed
agentmeter/tracker.py
agentmeter/utils.py
agentmeter/resources/__init__.py
agentmeter/resources/meter_events.py
agentmeter/resources/meter_types.py
agentmeter/resources/projects.py
agentmeter/resources/users.py
agentmeter/utils/__init__.py
agentmeter/utils/config.py
agentmeter/utils/retry.py
agentmeter/utils/validation.py
agentmeter-0.3.2.dist-info/licenses/LICENSE
agentmeter-0.3.2.dist-info/METADATA
agentmeter-0.3.2.dist-info/WHEEL
agentmeter-0.3.2.dist-info/entry_points.txt
agentmeter-0.3.2.dist-info/top_level.txt
agentmeter-0.3.2.dist-info/RECORD
