Metadata-Version: 2.4
Name: agentmeter
Version: 0.3.2
Summary: Python SDK for AgentMeter usage tracking and billing
Author-email: "AgentMeter.Money" <thomas.yu@knn3.xyz>
License-Expression: MIT
Project-URL: Homepage, https://agentmeter.money
Project-URL: Documentation, https://docs.agentmeter.money/sdk/python
Project-URL: Repository, https://github.com/Pagent-Money/agentmeter-sdk-python
Project-URL: Issues, https://github.com/Pagent-Money/agentmeter-sdk-python/issues
Project-URL: Changelog, https://github.com/Pagent-Money/agentmeter-sdk-python/blob/main/CHANGELOG.md
Keywords: billing,usage-tracking,metering,api-billing,token-billing,subscription,payments,agentmeter
Classifier: Development Status :: 4 - Beta
Classifier: Intended Audience :: Developers
Classifier: Operating System :: OS Independent
Classifier: Programming Language :: Python :: 3
Classifier: Programming Language :: Python :: 3.7
Classifier: Programming Language :: Python :: 3.8
Classifier: Programming Language :: Python :: 3.9
Classifier: Programming Language :: Python :: 3.10
Classifier: Programming Language :: Python :: 3.11
Classifier: Programming Language :: Python :: 3.12
Classifier: Topic :: Software Development :: Libraries :: Python Modules
Classifier: Topic :: Internet :: WWW/HTTP :: Dynamic Content
Classifier: Topic :: Office/Business :: Financial :: Accounting
Requires-Python: >=3.7
License-File: LICENSE
Requires-Dist: httpx>=0.24.0
Requires-Dist: pydantic>=2.0.0
Requires-Dist: typing-extensions>=4.5.0; python_version < "3.8"
Provides-Extra: langchain
Requires-Dist: langchain-core>=0.1.0; extra == "langchain"
Provides-Extra: dev
Requires-Dist: pytest>=7.0.0; extra == "dev"
Requires-Dist: pytest-asyncio>=0.21.0; extra == "dev"
Requires-Dist: pytest-cov>=4.0.0; extra == "dev"
Requires-Dist: black>=23.0.0; extra == "dev"
Requires-Dist: isort>=5.12.0; extra == "dev"
Requires-Dist: flake8>=6.0.0; extra == "dev"
Requires-Dist: mypy>=1.0.0; extra == "dev"
Requires-Dist: pre-commit>=3.0.0; extra == "dev"
Provides-Extra: docs
Requires-Dist: sphinx>=4.0; extra == "docs"
Requires-Dist: sphinx-rtd-theme>=1.0; extra == "docs"
Requires-Dist: myst-parser>=0.18; extra == "docs"
Dynamic: license-file
